Metadata-Version: 1.1
Name: acudpclient
Version: 1.1.0
Summary: Assetto Corsa UDP Client
Home-page: https://b.joaoubaldo.com
Author: Joao Coutinho
Author-email: me@joaoubaldo.com
License: UNKNOWN
Keywords: assetto-corsa dedicated-server client udp
Platform: UNKNOWN
Classifier: Programming Language :: Python
